skpf/__init__.py
skpf/tools/__init__.py
skpf/tools/planners.py
skpf/tools/utils.py
skpf/yamls/stepwise.yaml
tests/__init__.py
tests/mathskills.py
tests/test_planner.py
skpf-0.0.6.dist-info/METADATA
skpf-0.0.6.dist-info/WHEEL
skpf-0.0.6.dist-info/entry_points.txt
skpf-0.0.6.dist-info/top_level.txt
skpf-0.0.6.dist-info/RECORD
