Metadata-Version: 2.1
Name: skpf
Version: 0.0.6
Summary: This package contains promptflow tools for working with Smenatic Kernel.
Requires-Dist: semantic-kernel
